ADPOS/Auth.py
ADPOS/__init__.py
ADPOSPythonSDK-1.1.1.dist-info/LICENSE
ADPOSPythonSDK-1.1.1.dist-info/METADATA
ADPOSPythonSDK-1.1.1.dist-info/WHEEL
ADPOSPythonSDK-1.1.1.dist-info/top_level.txt
ADPOSPythonSDK-1.1.1.dist-info/RECORD
