Metadata-Version: 2.2
Name: ADPOSPythonSDK
Version: 1.1.1
Summary: AdrianDevProjects Online Services Python SDK
Home-page: https://github.com/adriandevprojects/ADPOSPythonSDK
Author: Adrian Albrecht
Author-email: adriandevprojects@gmail.com
License: GPL-3.0
License-File: LICENSE
Dynamic: author
Dynamic: author-email
Dynamic: description
Dynamic: description-content-type
Dynamic: home-page
Dynamic: license
Dynamic: summary
